{
  "project_info": {
    "project_number": "328012629085",
    "project_id": "restrosupplyhub",
    "storage_bucket": "restrosupplyhub.appspot.com"
  },
  "client": [
    {
      "client_info": {
        "mobilesdk_app_id": "1:328012629085:android:6cf4ab50cb96f4fe76f9b4",
        "android_client_info": {
          "package_name": "com.restrosupply.hub"
        }
      },
      "oauth_client": [],
      "api_key": [
        {
          "current_key": "AIzaSyDYG4bXxET9fEeA-H_k5khvax81LhDlJHI"
        }
      ],
      "services": {
        "appinvite_service": {
          "other_platform_oauth_client": []
        }
      }
    }
  ],
  "configuration_version": "1"
}